ceng/__init__.py
ceng/common.py
ceng/interp.py
ceng/load.py
ceng/lookup.py
ceng-0.5.dist-info/LICENSE
ceng-0.5.dist-info/WHEEL
ceng-0.5.dist-info/METADATA
ceng-0.5.dist-info/RECORD
