Metadata-Version: 2.1
Name: ceng
Version: 0.5
Summary: Tool for Coding Tasks Specific to Civil Engineering
Author-email: Ricky L Teachey Jr <ricky@teachey.org>
Requires-Python: >=3.9
Classifier: Intended Audience :: Other Audience
Classifier: License :: OSI Approved :: MIT License
Classifier: Programming Language :: Python :: 3
Classifier: Topic :: Scientific/Engineering
Classifier: Development Status :: 2 - Pre-Alpha
Requires-Dist: numpy >=1.20
Requires-Dist: scipy >=1.7
Requires-Dist: wrapt >= 1.13
Requires-Dist: numba
Requires-Dist: pytest >=6.2 ; extra == "test"
Project-URL: Home, https://github.com/ricyteach/ceng
Provides-Extra: test
